anaplan/__init__.py
anaplan-2.6.2.dist-info/METADATA
anaplan-2.6.2.dist-info/WHEEL
anaplan-2.6.2.dist-info/top_level.txt
anaplan-2.6.2.dist-info/RECORD
