Metadata-Version: 2.1
Name: anaplan
Version: 2.6.2
Summary: PyerualJetwork is a machine learning library written in Python for professionals, incorporating advanced, unique, new, and modern techniques.
Author: Hasan Can Beydili
Author-email: tchasancan@gmail.com
Keywords: model evaluation,classification,potentiation learning artificial neural networks,NEAT,genetic algorithms,reinforcement learning,neural networks
